assets/phalanx_banner.jpg
phnx/__init__.py
phnx/cli.py
phnx/downloader/__init__.py
phnx/downloader/base.py
phnx/downloader/defaults.json
phnx/downloader/fragment_downloader.py
phnx/downloader/utils.py
phnx/downloader/volume_downloader.py
vesuvius_phalanx-0.1.13.dist-info/licenses/LICENSE
vesuvius_phalanx-0.1.13.dist-info/METADATA
vesuvius_phalanx-0.1.13.dist-info/WHEEL
vesuvius_phalanx-0.1.13.dist-info/entry_points.txt
vesuvius_phalanx-0.1.13.dist-info/top_level.txt
vesuvius_phalanx-0.1.13.dist-info/RECORD
