Metadata-Version: 2.4
Name: vesuvius-phalanx
Version: 0.1.13
Author-email: Marcel Roth <marcelroth100@aol.com>
License:  The MIT License (MIT)
Project-URL: Homepage, https://github.com/mvrcii/phalanx
Classifier: Programming Language :: Python :: 3
Classifier: Programming Language :: Python :: 3.8
Classifier: Operating System :: OS Independent
Requires-Python: >=3.8
License-File: LICENSE
Requires-Dist: requests
Requires-Dist: beautifulsoup4
Requires-Dist: tqdm
Requires-Dist: click
Requires-Dist: rich
Dynamic: license-file
